blaseball_mike/__init__.py
blaseball_mike/database.py
blaseball_mike/events.py
blaseball_mike/eventually.py
blaseball_mike/reference.py
blaseball_mike/session.py
blaseball_mike/stream_model.py
blaseball_mike/tables.py
blaseball_mike/utils.py
blaseball_mike/chronicler/__init__.py
blaseball_mike/chronicler/chron_helpers.py
blaseball_mike/chronicler/v1.py
blaseball_mike/chronicler/v2.py
blaseball_mike/models/__init__.py
blaseball_mike/models/base.py
blaseball_mike/models/election.py
blaseball_mike/models/feed.py
blaseball_mike/models/fight.py
blaseball_mike/models/game.py
blaseball_mike/models/global_event.py
blaseball_mike/models/item.py
blaseball_mike/models/leaderboard.py
blaseball_mike/models/league.py
blaseball_mike/models/modification.py
blaseball_mike/models/player.py
blaseball_mike/models/playoff.py
blaseball_mike/models/season.py
blaseball_mike/models/simulation_data.py
blaseball_mike/models/stadium.py
blaseball_mike/models/statsheet.py
blaseball_mike/models/team.py
blaseball_mike/models/weather.py
tests/__init__.py
tests/conftest.py
tests/helpers.py
tests/test_base.py
tests/test_chronicler.py
tests/test_election.py
tests/test_event_stream.py
tests/test_feed.py
tests/test_fight.py
tests/test_game.py
tests/test_items.py
tests/test_leaderboards.py
tests/test_league.py
tests/test_misc.py
tests/test_player.py
tests/test_playoffs.py
tests/test_stadium.py
tests/test_statsheets.py
tests/test_team.py
blaseball_mike-6.11.0.dist-info/LICENSE
blaseball_mike-6.11.0.dist-info/METADATA
blaseball_mike-6.11.0.dist-info/WHEEL
blaseball_mike-6.11.0.dist-info/top_level.txt
blaseball_mike-6.11.0.dist-info/RECORD
