Metadata-Version: 2.1
Name: blaseball-mike
Version: 6.11.0
Summary: Read-only Python wrapper around blaseball game API
Home-page: https://github.com/jmaliksi/blaseball-mike
Author: Joe Maliksi
Author-email: joe.maliksi@gmail.com
License: UNKNOWN
Platform: UNKNOWN
Requires-Python: ~=3.8
License-File: LICENSE
Requires-Dist: aiohttp
Requires-Dist: aiohttp-sse-client
Requires-Dist: python-dateutil
Requires-Dist: requests
Requires-Dist: ujson
Requires-Dist: requests-cache
